byted_overpass_flow_ide_knowledgebase_bd/__init__.py
byted_overpass_flow_ide_knowledgebase_bd-0.0.1.dist-info/METADATA
byted_overpass_flow_ide_knowledgebase_bd-0.0.1.dist-info/WHEEL
byted_overpass_flow_ide_knowledgebase_bd-0.0.1.dist-info/top_level.txt
byted_overpass_flow_ide_knowledgebase_bd-0.0.1.dist-info/RECORD
